yolo_world/__init__.py
yolo_world/version.py
yolo_world/datasets/__init__.py
yolo_world/datasets/mm_dataset.py
yolo_world/datasets/utils.py
yolo_world/datasets/yolov5_lvis.py
yolo_world/datasets/yolov5_mixed_grounding.py
yolo_world/datasets/yolov5_obj365v1.py
yolo_world/datasets/yolov5_obj365v2.py
yolo_world/datasets/yolov5_v3det.py
yolo_world/datasets/transformers/__init__.py
yolo_world/datasets/transformers/mm_mix_img_transforms.py
yolo_world/datasets/transformers/mm_transforms.py
yolo_world/engine/__init__.py
yolo_world/engine/optimizers/__init__.py
yolo_world/engine/optimizers/yolow_v5_optim_constructor.py
yolo_world/models/__init__.py
yolo_world/models/assigner/__init__.py
yolo_world/models/assigner/task_aligned_assigner.py
yolo_world/models/backbones/__init__.py
yolo_world/models/backbones/mm_backbone.py
yolo_world/models/data_preprocessors/__init__.py
yolo_world/models/data_preprocessors/data_preprocessor.py
yolo_world/models/dense_heads/__init__.py
yolo_world/models/dense_heads/yolo_world_head.py
yolo_world/models/dense_heads/yolo_world_seg_head.py
yolo_world/models/detectors/__init__.py
yolo_world/models/detectors/yolo_world.py
yolo_world/models/layers/__init__.py
yolo_world/models/layers/yolo_bricks.py
yolo_world/models/losses/__init__.py
yolo_world/models/losses/dynamic_loss.py
yolo_world/models/necks/__init__.py
yolo_world/models/necks/yolo_world_pafpn.py
yolo_world_open-0.10.0.dist-info/LICENSE
yolo_world_open-0.10.0.dist-info/METADATA
yolo_world_open-0.10.0.dist-info/WHEEL
yolo_world_open-0.10.0.dist-info/top_level.txt
yolo_world_open-0.10.0.dist-info/zip-safe
yolo_world_open-0.10.0.dist-info/RECORD
