Metadata-Version: 2.1
Name: yolo_world_open
Version: 0.10.0
Summary: YOLO-World: Real-time Open Vocabulary Object Detection
Author-email: Tencent AILab <ronnysong@tencent.com>
License: Apache License 2.0
Keywords: object detection
Classifier: Development Status :: 4 - Beta
Classifier: License :: OSI Approved :: Apache Software License
Classifier: Operating System :: OS Independent
Classifier: Programming Language :: Python :: 3
Classifier: Programming Language :: Python :: 3.7
Classifier: Programming Language :: Python :: 3.8
Classifier: Programming Language :: Python :: 3.9
Classifier: Programming Language :: Python :: 3.10
Classifier: Programming Language :: Python :: 3.11
Classifier: Topic :: Scientific/Engineering :: Artificial Intelligence
Requires-Python: >=3.7
License-File: LICENSE
Requires-Dist: opencv-python-headless
Requires-Dist: wheel
Requires-Dist: torch ==2.1.0
Requires-Dist: torchvision
Requires-Dist: transformers ==4.36.2
Requires-Dist: tokenizers
Requires-Dist: numpy <2.0.0
Requires-Dist: supervision ==0.19.0
Requires-Dist: mmdet-open
Requires-Dist: mmengine-open
Requires-Dist: mmyolo-open
Requires-Dist: mmcv-open2
